setup.cfg
setup.py
SolverByPina/__init__.py
SolverByPina.egg-info/PKG-INFO
SolverByPina.egg-info/SOURCES.txt
SolverByPina.egg-info/dependency_links.txt
SolverByPina.egg-info/top_level.txt